sample_alacater/__init__.py
sample_alacater-0.1.1.dist-info/METADATA
sample_alacater-0.1.1.dist-info/WHEEL
sample_alacater-0.1.1.dist-info/RECORD
